README.md
setup.py
cABCanalysis/__init__.py
cABCanalysis/cABCanalysis.py
cABCanalysis.egg-info/PKG-INFO
cABCanalysis.egg-info/SOURCES.txt
cABCanalysis.egg-info/dependency_links.txt
cABCanalysis.egg-info/not-zip-safe
cABCanalysis.egg-info/requires.txt
cABCanalysis.egg-info/top_level.txt