Metadata-Version: 2.1
Name: cABCanalysis
Version: 0.1.1
Summary: Nested computed ABC analysis (cABC): A method to reduce feature sets to their most relevant items. Implementation in Python.
Home-page: https://github.com/JornLotsch/ABCanalysis
Author: Jorn Lotsch
Author-email: j.loetsch@em.uni-frankfurt.de
License: GNU General Public License v3 (GPLv3)
Keywords: cABC analysis,ABC analysis,item categorization,feature selection,information reduction
Platform: UNKNOWN
Classifier: Intended Audience :: Science/Research
Classifier: Programming Language :: Python :: 3
Classifier: Operating System :: MacOS :: MacOS X
Classifier: Operating System :: Microsoft :: Windows
Classifier: Operating System :: POSIX :: Linux
Requires-Python: >=3.5
